SJ_CONSTANTS/__init__.py
SJ_CONSTANTS/constants.py
tests/__init__.py
tests/test_verifier.py
SJ_CONSTANTS-0.0.1.dist-info/LICENSE
SJ_CONSTANTS-0.0.1.dist-info/METADATA
SJ_CONSTANTS-0.0.1.dist-info/WHEEL
SJ_CONSTANTS-0.0.1.dist-info/top_level.txt
SJ_CONSTANTS-0.0.1.dist-info/RECORD
